{"symbols":{"CounterState":{"hasNamespace":false,"type":1,"moduleName":"counter","relativePath":"react/src/store/slices/counter"},"Firebase":{"hasNamespace":false,"type":0,"moduleName":"firebase","relativePath":"react/src/lib/firebase"},"NotificationAdd":{"hasNamespace":false,"type":1,"moduleName":"notifications","relativePath":"react/src/store/slices/notifications"},"Notification":{"hasNamespace":false,"type":1,"moduleName":"notifications","relativePath":"react/src/store/slices/notifications"}},"files":{"my-react/src/setupTests.ts":"2021-11-29T20:44:02.855Z","my-react/src/react-app-env.d.ts":"2021-11-29T20:44:08.127Z","my-react/src/reportWebVitals.ts":"2021-11-29T20:44:02.855Z","react/src/react-app-env.d.ts":"2021-11-29T20:44:08.127Z","react/src/setupTests.ts":"2021-11-29T20:44:02.855Z","react/src/reportWebVitals.ts":"2021-12-15T21:42:33.769Z","react/src/hooks/useUsers.ts":"2021-12-17T11:10:36.400Z","react/src/types/Activity.ts":"2021-12-18T21:34:29.768Z","react/src/types/User.ts":"2021-12-15T21:30:31.150Z","react/src/store/index.ts":"2021-12-18T21:29:41.374Z","react/src/store/slices/activities.ts":"2021-12-20T13:39:24.983Z","react/src/store/slices/notifications.ts":"2021-12-20T13:58:41.621Z","react/src/api/firebase.ts":"2021-12-15T21:06:30.106Z","react/src/lib/firebase.ts":"2021-12-17T15:53:36.014Z","react/src/store/slices/auth.ts":"2021-12-20T13:39:24.983Z","react/src/store/slices/users.ts":"2021-12-20T10:12:28.886Z","react/src/types/globals.ts":"2021-12-19T12:52:15.869Z","react/src/services/usersApi.ts":"2021-12-20T14:01:53.130Z","react/src/hooks/useNotifications.ts":"2021-12-20T13:46:37.797Z"}}